baiducloud/__init__.py
baiducloud/client.py
baiducloud/others.py
baiducloud-1.0.8.dist-info/LICENSE
baiducloud-1.0.8.dist-info/LICENSE.txt
baiducloud-1.0.8.dist-info/METADATA
baiducloud-1.0.8.dist-info/WHEEL
baiducloud-1.0.8.dist-info/top_level.txt
baiducloud-1.0.8.dist-info/RECORD
